LICENSE
MANIFEST.in
README.md
requirements.txt
setup.py
pytest_db/__init__.py
pytest_db/mysql_client.py
pytest_db/plugin.py
pytest_db.egg-info/PKG-INFO
pytest_db.egg-info/SOURCES.txt
pytest_db.egg-info/dependency_links.txt
pytest_db.egg-info/entry_points.txt
pytest_db.egg-info/requires.txt
pytest_db.egg-info/top_level.txt
pytest_db.egg-info/zip-safe
tests/test_pytest_db.py